autora/experimentalist/sampler/model_disagreement_sampler/__init__.py
autora_experimentalist_sampler_model_disagreement_sampler-1.0.0rc0.dist-info/METADATA
autora_experimentalist_sampler_model_disagreement_sampler-1.0.0rc0.dist-info/WHEEL
autora_experimentalist_sampler_model_disagreement_sampler-1.0.0rc0.dist-info/top_level.txt
autora_experimentalist_sampler_model_disagreement_sampler-1.0.0rc0.dist-info/RECORD
