Metadata-Version: 2.1
Name: autora-experimentalist-sampler-model-disagreement-sampler
Version: 1.0.0rc0
Summary: Compares weaknesses in multiple models
Author-email: "Built by Sebastian Musslick, re-factored by Chad Williams" <sebastian_musslick@brown.edu>
License: MIT license
Project-URL: homepage, http://www.empiricalresearch.ai
Project-URL: repository, https://github.com/AutoResearch/autora-experimentalist-sampler-model-disagreement-sampler.git
Project-URL: documentation, https://autoresearch.github.io/autora/
Requires-Python: <4,>=3.8
Requires-Dist: autora-core
Requires-Dist: scikit-learn
Provides-Extra: dev
Requires-Dist: autora-core[dev] ; extra == 'dev'
